{
  "version": 2,
  "projects": {
    "demo-app": {
      "root": "apps/demo-app",
      "sourceRoot": "apps/demo-app/src",
      "projectType": "application",
      "targets": {
        "build": {
          "executor": "@nrwl/webpack:webpack",
          "outputs": ["{options.outputPath}"],
          "options": {
            "outputPath": "dist/apps/demo-app",
            "index": "apps/demo-app/src/index.html",
            "main": "apps/demo-app/src/main.tsx",
            "tsConfig": "apps/demo-app/tsconfig.app.json",
            "assets": [
              "apps/demo-app/src/favicon.ico",
              "apps/demo-app/src/assets"
            ],
            "styles": ["apps/demo-app/src/styles.css"]
          }
        },
        "serve": {
          "executor": "@nrwl/webpack:dev-server",
          "options": {
            "buildTarget": "demo-app:build"
          }
        }
      }
    }
  }
}
